README.md
setup.py
scrapy_redis_bloomfilter_block_cluster/__init__.py
scrapy_redis_bloomfilter_block_cluster/bloomfilter.py
scrapy_redis_bloomfilter_block_cluster/connection.py
scrapy_redis_bloomfilter_block_cluster/defaults.py
scrapy_redis_bloomfilter_block_cluster/dupefilter.py
scrapy_redis_bloomfilter_block_cluster/extensions.py
scrapy_redis_bloomfilter_block_cluster/picklecompat.py
scrapy_redis_bloomfilter_block_cluster/pipelines.py
scrapy_redis_bloomfilter_block_cluster/queue.py
scrapy_redis_bloomfilter_block_cluster/scheduler.py
scrapy_redis_bloomfilter_block_cluster/spiders.py
scrapy_redis_bloomfilter_block_cluster/utils.py
scrapy_redis_bloomfilter_block_cluster.egg-info/PKG-INFO
scrapy_redis_bloomfilter_block_cluster.egg-info/SOURCES.txt
scrapy_redis_bloomfilter_block_cluster.egg-info/dependency_links.txt
scrapy_redis_bloomfilter_block_cluster.egg-info/requires.txt
scrapy_redis_bloomfilter_block_cluster.egg-info/top_level.txt